README.rst
setup.py
caelum/__init__.py
caelum/eere.csv
caelum/eere.py
caelum/eere_meta.csv
caelum/env.py
caelum/fix.txt
caelum/forecast.py
caelum/g.py
caelum/g2.py
caelum/g3.py
caelum/gfs.py
caelum/inswo-stns.txt
caelum/noaa.py
caelum/notfound.csv
caelum/nsrdb.py
caelum/t.py
caelum/tmy3.csv
caelum/tmy3.py
caelum/tools.py
caelum.egg-info/PKG-INFO
caelum.egg-info/SOURCES.txt
caelum.egg-info/dependency_links.txt
caelum.egg-info/pbr.json
caelum.egg-info/requires.txt
caelum.egg-info/top_level.txt
tests/__init__.py
tests/cover.py
tests/unit.py