Metadata-Version: 1.1
Name: caelum
Version: 0.8.25.18
Summary: library for weather sources (historical and forecasted)
Home-page: https://github.com/nrcharles/caelum
Author: Nathan Charles
Author-email: ncharles@gmail.com
License: LGPL
Keywords: climate weather data TMY EPW EERE
Platform: UNKNOWN
Classifier: Development Status :: 4 - Beta
Classifier: License :: OSI Approved :: GNU Library or Lesser General Public License (LGPL)
